edk_tools/__init__.py
edk_tools/edk_crypto.py
edk_tools/edk_log.py
edk_tools/pkg_command/__init__.py
edk_tools/pkg_command/edk_command.py
edk_tools-0.0.13.data/scripts/mmo
edk_tools-0.0.13.data/scripts/wow
edk_tools-0.0.13.dist-info/LICENSE
edk_tools-0.0.13.dist-info/METADATA
edk_tools-0.0.13.dist-info/WHEEL
edk_tools-0.0.13.dist-info/entry_points.txt
edk_tools-0.0.13.dist-info/top_level.txt
edk_tools-0.0.13.dist-info/RECORD
